fusion_neutron_utils-0.1.3.dist-info/METADATA
fusion_neutron_utils-0.1.3.dist-info/WHEEL
fusion_neutron_utils-0.1.3.dist-info/licenses/LICENSE
fusion_neutron_utils/__init__.py
fusion_neutron_utils/fusion_neutron_utils.cpython-310-aarch64-linux-gnu.so
fusion_neutron_utils-0.1.3.dist-info/RECORD
