Metadata-Version: 2.3
Name: fusion_neutron_utils
Version: 0.1.3
Classifier: Programming Language :: Rust
Classifier: Programming Language :: Python :: Implementation :: CPython
Classifier: Programming Language :: Python :: Implementation :: PyPy
Requires-Dist: pytest ; extra == 'tests'
Requires-Dist: scipy ==1.13.1 ; extra == 'tests'
Provides-Extra: tests
License-File: LICENSE
Requires-Python: >=3.8
